libraslib/__init__.py
libraslib/librasfunction.py
libraslib/testscript.py
LibrasLib-0.0.1.dist-info/LICENSE.txt
LibrasLib-0.0.1.dist-info/METADATA
LibrasLib-0.0.1.dist-info/WHEEL
LibrasLib-0.0.1.dist-info/top_level.txt
LibrasLib-0.0.1.dist-info/RECORD
