Metadata-Version: 2.1
Name: LibrasLib
Version: 0.0.1
Summary: Biblioteca de interpretação em LIBRAS
Home-page: https://github.com/amanemedeiros/libraslib
Author: Amanda Batista Medeiros
Author-email: amandamedeiros.ufsc@gmail.com
License: UNKNOWN
Platform: UNKNOWN
Classifier: Programming Language :: Python :: 3
Classifier: License :: OSI Approved :: MIT License
Classifier: Operating System :: OS Independent
Requires-Python: >=3.8
